ble_serial/__init__.py
ble_serial/__main__.py
ble_serial/cli.py
ble_serial/main.py
ble_serial/bluetooth/__init__.py
ble_serial/bluetooth/ble_client.py
ble_serial/bluetooth/ble_server.py
ble_serial/bluetooth/constants.py
ble_serial/bluetooth/interface.py
ble_serial/bluetooth/uuid_helpers.py
ble_serial/log/console_log.py
ble_serial/log/fs_log.py
ble_serial/ports/interface.py
ble_serial/ports/linux_pty.py
ble_serial/ports/print_dummy.py
ble_serial/ports/tcp_socket.py
ble_serial/ports/windows_com0com.py
ble_serial/scan/__init__.py
ble_serial/scan/__main__.py
ble_serial/scan/main.py
ble_serial/setup_com0com/__init__.py
ble_serial/setup_com0com/__main__.py
ble_serial/setup_com0com/windows_priv_setupc.py
ble_serial-3.0.0.dist-info/METADATA
ble_serial-3.0.0.dist-info/WHEEL
ble_serial-3.0.0.dist-info/entry_points.txt
ble_serial-3.0.0.dist-info/licenses/LICENSE
ble_serial-3.0.0.dist-info/RECORD
