Metadata-Version: 2.3
Name: ble-serial
Version: 3.0.0
Summary: Connects BLE adapters with virtual serial ports
Project-URL: Homepage, https://github.com/Jakeler/ble-serial
Project-URL: Repository, https://github.com/Jakeler/ble-serial
Project-URL: Issues, https://github.com/Jakeler/ble-serial/issues
Project-URL: Changelog, https://github.com/Jakeler/ble-serial/releases
Author-email: Jake <ble-serial-pypi@ja-ke.tech>
License: MIT License
Classifier: Environment :: Console
Classifier: Intended Audience :: Developers
Classifier: License :: OSI Approved :: MIT License
Classifier: Operating System :: MacOS :: MacOS X
Classifier: Operating System :: Microsoft :: Windows
Classifier: Operating System :: POSIX :: Linux
Classifier: Operating System :: Unix
Classifier: Programming Language :: Python
Classifier: Programming Language :: Python :: 3
Classifier: Programming Language :: Python :: 3.8
Classifier: Programming Language :: Python :: 3.9
Classifier: Programming Language :: Python :: 3.10
Classifier: Programming Language :: Python :: 3.11
Classifier: Programming Language :: Python :: 3.12
Classifier: Topic :: Utilities
Requires-Python: >=3.8
Requires-Dist: bleak>=0.20.0
Requires-Dist: coloredlogs>=15.0
Requires-Dist: pyserial>=3.5; sys_platform == 'win32'
Provides-Extra: server
Requires-Dist: bless>=0.2.6; extra == 'server'
Requires-Dist: pysetupdi; (sys_platform == 'win32') and extra == 'server'
